AUTHORS
CHANGELOG.md
LICENSE
MANIFEST.in
README.md
requirements.txt
setup.py
django_tailordev_cms.egg-info/PKG-INFO
django_tailordev_cms.egg-info/SOURCES.txt
django_tailordev_cms.egg-info/dependency_links.txt
django_tailordev_cms.egg-info/not-zip-safe
django_tailordev_cms.egg-info/requires.txt
django_tailordev_cms.egg-info/top_level.txt
requirements/compiled.txt
requirements/local.txt
requirements/production.txt
td_cms/__init__.py
td_cms/abstract_models.py
td_cms/admin.py
td_cms/factories.py
td_cms/models.py
td_cms/translation.py
td_cms/urls.py
td_cms/views.py
td_cms/locale/en/LC_MESSAGES/django.mo
td_cms/locale/en/LC_MESSAGES/django.po
td_cms/locale/fr/LC_MESSAGES/django.mo
td_cms/locale/fr/LC_MESSAGES/django.po
td_cms/management/__init__.py
td_cms/management/commands/__init__.py
td_cms/management/commands/cms_lorem_fixtures.py
td_cms/migrations/0001_initial.py
td_cms/migrations/0002_auto__add_field_category_position.py
td_cms/migrations/0003_auto__add_field_allow_comments.py
td_cms/migrations/0004_auto__add_field_page_position.py
td_cms/migrations/0005_auto__add_field_page_allow_sharing.py
td_cms/migrations/__init__.py
td_cms/static/td_cms/css/styles.css
td_cms/static/td_cms/javascripts/vendor/tinymce_setup.js
td_cms/static/td_cms/scss/_mixins.scss
td_cms/static/td_cms/scss/_tinymce.scss
td_cms/static/td_cms/scss/styles.scss
td_cms/templates/td_cms/category_detail.html
td_cms/templates/td_cms/page_detail.html
td_cms/templates/td_cms/layouts/one_col.html
td_cms/templates/td_cms/layouts/sidebar_block.html
td_cms/templates/td_cms/layouts/three_cols.html
td_cms/templates/td_cms/layouts/two_cols_left_sidebar.html
td_cms/templates/td_cms/layouts/two_cols_right_sidebar.html
td_cms/templates/td_cms/partials/foundation_topbar.html
td_cms/templates/td_cms/partials/page_social.html
td_cms/templates/td_cms/partials/pagination.html
td_cms/templates/td_cms/partials/comments/disqus_thread.html
td_cms/templates/td_cms/partials/main_content/category_detail.html
td_cms/templates/td_cms/partials/main_content/page_detail.html
td_cms/templates/td_cms/partials/sidebar/category_list.html
td_cms/templates/td_cms/partials/sidebar/top_articles_list.html
td_cms/templatetags/__init__.py
td_cms/templatetags/td_cms_tags.py
td_cms/tests/__init__.py
