Metadata-Version: 1.1
Name: django-tailordev-cms
Version: 0.7.5
Summary: TailorDev CMS  A simple CMS for your django projects.
Home-page: https://bitbucket.org/tailordev/django-tailordev-cms
Author: Julien Maupetit
Author-email: julien@tailordev.com
License: MIT
Platform: UNKNOWN
Classifier: Topic :: Internet :: WWW/HTTP :: Dynamic Content
Classifier: Intended Audience :: Developers
Classifier: Programming Language :: Python
Classifier: Programming Language :: Python :: 2.6
Classifier: Programming Language :: Python :: 2.7
Classifier: Framework :: Django
Classifier: Development Status :: 4 - Beta
Classifier: Operating System :: OS Independent
